pullify-2.3.4.dist-info/licenses/AUTHORS.rst
pullify-2.3.4.dist-info/licenses/LICENSE
savify/__init__.py
savify/__main__.py
savify/cli.py
savify/exceptions.py
savify/ffmpegdl.py
savify/logger.py
savify/savify.py
savify/spotify.py
savify/track.py
savify/types.py
savify/utils.py
pullify-2.3.4.dist-info/METADATA
pullify-2.3.4.dist-info/WHEEL
pullify-2.3.4.dist-info/entry_points.txt
pullify-2.3.4.dist-info/top_level.txt
pullify-2.3.4.dist-info/RECORD
