Metadata-Version: 2.4
Name: pullify
Version: 2.3.4
Summary: Download Spotify songs to mp3 with full metadata and cover art!
Home-page: https://github.com/LaurenceRawlings/savify
Author: Laurence Rawlings
Author-email: contact@laurencerawlings.com
License: MIT license
Keywords: pullify,savify,spotify,downloader,mp3,save,playlist
Classifier: Development Status :: 2 - Pre-Alpha
Classifier: Intended Audience :: Developers
Classifier: License :: OSI Approved :: MIT License
Classifier: Natural Language :: English
Classifier: Programming Language :: Python :: 3
Classifier: Programming Language :: Python :: 3.6
Classifier: Programming Language :: Python :: 3.7
Classifier: Programming Language :: Python :: 3.8
Requires-Python: >=3.6
License-File: LICENSE
License-File: AUTHORS.rst
Requires-Dist: ffmpy>=0.3.0
Requires-Dist: spotipy>=2.16.1
Requires-Dist: tldextract>=3.1.0
Requires-Dist: validators>=0.18.2
Requires-Dist: youtube-dl>=2021.6.6
Requires-Dist: requests>=2.25.1
Requires-Dist: click>=7.1.2
Dynamic: author
Dynamic: author-email
Dynamic: classifier
Dynamic: description
Dynamic: home-page
Dynamic: keywords
Dynamic: license
Dynamic: license-file
Dynamic: requires-dist
Dynamic: requires-python
Dynamic: summary
